Workbook

Sheet Assumptions
B2: TOLL ROAD BOT CONCESSION — PROJECT FINANCE MODEL
B3: Blue = input cell (edit these) | Black = formula | Yellow = key assumption driving returns
B5: PROJECT & TIMELINE
B6: Concession length — construction | C6: 2 | D6: years | E6: Typical 2-3 yr build for a 4-lane highway package
B7: Concession length — operations | C7: 20 | D7: years | E7: NHAI BOT concessions commonly run 15-30 yrs post-COD
B8: Highway length | C8: 60 | D8: km | E8: Placeholder — set from the concession agreement
B10: CAPITAL COST
B11: Base construction cost per km | C11: 95 | D11: INR mn/km | E11: ILLUSTRATIVE. Source from NHAI bid/NIP docs.
B12: Total project cost | C12: =C8*C11 | D12: INR mn | E12: Length x cost per km
B13: Capex split — construction year 1 | C13: 0.45 | E13: Drawdown profile across the build period
B14: Contingency on base cost | C14: 0.05 | E14: Cost overrun buffer
B16: TRAFFIC & TARIFF
B17: Opening year traffic (AADT) | C17: 24000 | D17: vehicles/day | E17: Annual Average Daily Traffic, all vehicle classes (PCU)
B18: Traffic CAGR | C18: 0.055 | E18: ILLUSTRATIVE. Ties to regional GDP/freight growth.
B19: Traffic ramp-up — year 1 of ops | C19: 0.75 | E19: Traffic builds to full run-rate over first 2-3 yrs
B20: Traffic ramp-up — year 2 of ops | C20: 0.9
B21: Blended toll per vehicle (opening) | C21: 115 | D21: INR/trip | E21: Weighted across car/LCV/truck mix
B22: Annual toll escalation | C22: 0.04 | E22: NHAI formula: ~3% + 40% of WPI inflation
B23: Toll leakage / exemptions | C23: 0.07 | E23: Local exempt traffic, evasion, FASTag failures
B25: OPERATING COST
B26: Routine O&M — year 1 of ops | C26: 210 | D26: INR mn | E26: Patrolling, toll plaza staffing, minor repairs
B27: O&M cost inflation | C27: 0.055
B28: Major maintenance cycle | C28: 5 | D28: years | E28: Periodic resurfacing / overlay
B29: Major maintenance cost (per event) | C29: 720 | D29: INR mn | E29: Bituminous overlay across full length
B31: FINANCING & TAX
B32: Debt share of project cost | C32: 0.7 | E32: 70:30 D/E is standard for Indian BOT/HAM
B33: Interest rate on debt | C33: 0.095 | E33: ILLUSTRATIVE. Set from term sheet.
B34: Debt tenor (post-COD) | C34: 15 | D34: years | E34: Amortising term loan
B35: Principal moratorium (post-COD) | C35: 2 | D35: years | E35: Standard in BOT — principal holiday during traffic ramp-up
B36: Corporate tax rate | C36: 0.25 | E36: India headline corporate rate (Sec 115BAA regime)
B37: Depreciation life (SLM) | C37: 20 | D37: years | E37: Straight line over concession
B38: Discount rate (WACC) | C38: 0.11 | E38: Blended cost of capital
B39: Cost of equity | C39: 0.15 | E39: Used for equity IRR benchmarking
B42: NOTE: every figure above is an illustrative placeholder. Replace with sourced values from a concession agreement, NHAI bid document or NIP project record before presenting this model.

Sheet Cash Flow
B2: CASH FLOW PROJECTION (INR mn)
B4: Year | C4: 1 | D4: 2 | E4: 3 | F4: 4 | G4: 5 | H4: 6 | I4: 7 | J4: 8 | K4: 9 | L4: 10 | M4: 11 | N4: 12 | O4: 13 | P4: 14 | Q4: 15 | R4: 16 | S4: 17 | T4: 18 | U4: 19 | V4: 20 | W4: 21 | X4: 22
B5: Phase | C5: Build | D5: Build | E5: Operate | F5: Operate | G5: Operate | H5: Operate | I5: Operate | J5: Operate | K5: Operate | L5: Operate | M5: Operate | N5: Operate | O5: Operate | P5: Operate | Q5: Operate | R5: Operate | S5: Operate | T5: Operate | U5: Operate | V5: Operate | W5: Operate | X5: Operate
B7: OPERATIONS
B8: Traffic (AADT, vehicles/day) | C8: 0 | D8: 0 | E8: =Assumptions!$C$17*(1+Assumptions!$C$18)^0*Assumptions!$C$19 | F8: =Assumptions!$C$17*(1+Assumptions!$C$18)^1*Assumptions!$C$20 | G8: =Assumptions!$C$17*(1+Assumptions!$C$18)^2*1 | H8: =Assumptions!$C$17*(1+Assumptions!$C$18)^3*1 | I8: =Assumptions!$C$17*(1+Assumptions!$C$18)^4*1 | J8: =Assumptions!$C$17*(1+Assumptions!$C$18)^5*1 | K8: =Assumptions!$C$17*(1+Assumptions!$C$18)^6*1 | L8: =Assumptions!$C$17*(1+Assumptions!$C$18)^7*1 | M8: =Assumptions!$C$17*(1+Assumptions!$C$18)^8*1 | N8: =Assumptions!$C$17*(1+Assumptions!$C$18)^9*1 | O8: =Assumptions!$C$17*(1+Assumptions!$C$18)^10*1 | P8: =Assumptions!$C$17*(1+Assumptions!$C$18)^11*1 | Q8: =Assumptions!$C$17*(1+Assumptions!$C$18)^12*1 | R8: =Assumptions!$C$17*(1+Assumptions!$C$18)^13*1 | S8: =Assumptions!$C$17*(1+Assumptions!$C$18)^14*1 | T8: =Assumptions!$C$17*(1+Assumptions!$C$18)^15*1 | U8: =Assumptions!$C$17*(1+Assumptions!$C$18)^16*1 | V8: =Assumptions!$C$17*(1+Assumptions!$C$18)^17*1 | W8: =Assumptions!$C$17*(1+Assumptions!$C$18)^18*1 | X8: =Assumptions!$C$17*(1+Assumptions!$C$18)^19*1
B9: Blended toll (INR/trip) | C9: 0 | D9: 0 | E9: =Assumptions!$C$21*(1+Assumptions!$C$22)^0 | F9: =Assumptions!$C$21*(1+Assumptions!$C$22)^1 | G9: =Assumptions!$C$21*(1+Assumptions!$C$22)^2 | H9: =Assumptions!$C$21*(1+Assumptions!$C$22)^3 | I9: =Assumptions!$C$21*(1+Assumptions!$C$22)^4 | J9: =Assumptions!$C$21*(1+Assumptions!$C$22)^5 | K9: =Assumptions!$C$21*(1+Assumptions!$C$22)^6 | L9: =Assumptions!$C$21*(1+Assumptions!$C$22)^7 | M9: =Assumptions!$C$21*(1+Assumptions!$C$22)^8 | N9: =Assumptions!$C$21*(1+Assumptions!$C$22)^9 | O9: =Assumptions!$C$21*(1+Assumptions!$C$22)^10 | P9: =Assumptions!$C$21*(1+Assumptions!$C$22)^11 | Q9: =Assumptions!$C$21*(1+Assumptions!$C$22)^12 | R9: =Assumptions!$C$21*(1+Assumptions!$C$22)^13 | S9: =Assumptions!$C$21*(1+Assumptions!$C$22)^14 | T9: =Assumptions!$C$21*(1+Assumptions!$C$22)^15 | U9: =Assumptions!$C$21*(1+Assumptions!$C$22)^16 | V9: =Assumptions!$C$21*(1+Assumptions!$C$22)^17 | W9: =Assumptions!$C$21*(1+Assumptions!$C$22)^18 | X9: =Assumptions!$C$21*(1+Assumptions!$C$22)^19
B10: Gross toll revenue | C10: 0 | D10: 0 | E10: =E8*E9*365/1000000 | F10: =F8*F9*365/1000000 | G10: =G8*G9*365/1000000 | H10: =H8*H9*365/1000000 | I10: =I8*I9*365/1000000 | J10: =J8*J9*365/1000000 | K10: =K8*K9*365/1000000 | L10: =L8*L9*365/1000000 | ... X10: =X8*X9*365/1000000
B11: Less: leakage / exemptions | C11: 0 | D11: 0 | E11: =-E10*Assumptions!$C$23 | F11: =-F10*Assumptions!$C$23 | G11: =-G10*Assumptions!$C$23 | H11: =-H10*Assumptions!$C$23 | I11: =-I10*Assumptions!$C$23 | J11: =-J10*Assumptions!$C$23 | K11: =-K10*Assumptions!$C$23 | L11: =-L10*Assumptions!$C$23 | ... X11: =-X10*Assumptions!$C$23
B12: Net toll revenue | C12: =C10+C11 | D12: =D10+D11 | E12: =E10+E11 | F12: =F10+F11 | G12: =G10+G11 | H12: =H10+H11 | I12: =I10+I11 | J12: =J10+J11 | ... X12: =X10+X11
B14: Routine O&M | C14: 0 | D14: 0 | E14: =-Assumptions!$C$26*(1+Assumptions!$C$27)^0 | F14: =-Assumptions!$C$26*(1+Assumptions!$C$27)^1 | G14: =-Assumptions!$C$26*(1+Assumptions!$C$27)^2 | H14: =-Assumptions!$C$26*(1+Assumptions!$C$27)^3 | I14: =-Assumptions!$C$26*(1+Assumptions!$C$27)^4 | J14: =-Assumptions!$C$26*(1+Assumptions!$C$27)^5 | K14: =-Assumptions!$C$26*(1+Assumptions!$C$27)^6 | L14: =-Assumptions!$C$26*(1+Assumptions!$C$27)^7 | M14: =-Assumptions!$C$26*(1+Assumptions!$C$27)^8 | N14: =-Assumptions!$C$26*(1+Assumptions!$C$27)^9 | O14: =-Assumptions!$C$26*(1+Assumptions!$C$27)^10 | P14: =-Assumptions!$C$26*(1+Assumptions!$C$27)^11 | Q14: =-Assumptions!$C$26*(1+Assumptions!$C$27)^12 | R14: =-Assumptions!$C$26*(1+Assumptions!$C$27)^13 | S14: =-Assumptions!$C$26*(1+Assumptions!$C$27)^14 | T14: =-Assumptions!$C$26*(1+Assumptions!$C$27)^15 | U14: =-Assumptions!$C$26*(1+Assumptions!$C$27)^16 | V14: =-Assumptions!$C$26*(1+Assumptions!$C$27)^17 | W14: =-Assumptions!$C$26*(1+Assumptions!$C$27)^18 | X14: =-Assumptions!$C$26*(1+Assumptions!$C$27)^19
B15: Major maintenance | C15: 0 | D15: 0 | E15: =IF(MOD(1,Assumptions!$C$28)=0,-Assumptions!$C$29*(1+Assumptions!$C$27)^1,0) | F15: =IF(MOD(2,Assumptions!$C$28)=0,-Assumptions!$C$29*(1+Assumptions!$C$27)^2,0) | G15: =IF(MOD(3,Assumptions!$C$28)=0,-Assumptions!$C$29*(1+Assumptions!$C$27)^3,0) | H15: =IF(MOD(4,Assumptions!$C$28)=0,-Assumptions!$C$29*(1+Assumptions!$C$27)^4,0) | I15: =IF(MOD(5,Assumptions!$C$28)=0,-Assumptions!$C$29*(1+Assumptions!$C$27)^5,0) | J15: =IF(MOD(6,Assumptions!$C$28)=0,-Assumptions!$C$29*(1+Assumptions!$C$27)^6,0) | K15: =IF(MOD(7,Assumptions!$C$28)=0,-Assumptions!$C$29*(1+Assumptions!$C$27)^7,0) | L15: =IF(MOD(8,Assumptions!$C$28)=0,-Assumptions!$C$29*(1+Assumptions!$C$27)^8,0) | M15: =IF(MOD(9,Assumptions!$C$28)=0,-Assumptions!$C$29*(1+Assumptions!$C$27)^9,0) | N15: =IF(MOD(10,Assumptions!$C$28)=0,-Assumptions!$C$29*(1+Assumptions!$C$27)^10,0) | O15: =IF(MOD(11,Assumptions!$C$28)=0,-Assumptions!$C$29*(1+Assumptions!$C$27)^11,0) | P15: =IF(MOD(12,Assumptions!$C$28)=0,-Assumptions!$C$29*(1+Assumptions!$C$27)^12,0) | Q15: =IF(MOD(13,Assumptions!$C$28)=0,-Assumptions!$C$29*(1+Assumptions!$C$27)^13,0) | R15: =IF(MOD(14,Assumptions!$C$28)=0,-Assumptions!$C$29*(1+Assumptions!$C$27)^14,0) | S15: =IF(MOD(15,Assumptions!$C$28)=0,-Assumptions!$C$29*(1+Assumptions!$C$27)^15,0) | T15: =IF(MOD(16,Assumptions!$C$28)=0,-Assumptions!$C$29*(1+Assumptions!$C$27)^16,0) | U15: =IF(MOD(17,Assumptions!$C$28)=0,-Assumptions!$C$29*(1+Assumptions!$C$27)^17,0) | V15: =IF(MOD(18,Assumptions!$C$28)=0,-Assumptions!$C$29*(1+Assumptions!$C$27)^18,0) | W15: =IF(MOD(19,Assumptions!$C$28)=0,-Assumptions!$C$29*(1+Assumptions!$C$27)^19,0) | X15: =IF(MOD(20,Assumptions!$C$28)=0,-Assumptions!$C$29*(1+Assumptions!$C$27)^20,0)
B16: Major maintenance reserve accrual | C16: 0 | D16: 0 | E16: =-Assumptions!$C$29*(1+Assumptions!$C$27)^0/Assumptions!$C$28 | F16: =-Assumptions!$C$29*(1+Assumptions!$C$27)^1/Assumptions!$C$28 | G16: =-Assumptions!$C$29*(1+Assumptions!$C$27)^2/Assumptions!$C$28 | H16: =-Assumptions!$C$29*(1+Assumptions!$C$27)^3/Assumptions!$C$28 | I16: =-Assumptions!$C$29*(1+Assumptions!$C$27)^4/Assumptions!$C$28 | J16: =-Assumptions!$C$29*(1+Assumptions!$C$27)^5/Assumptions!$C$28 | K16: =-Assumptions!$C$29*(1+Assumptions!$C$27)^6/Assumptions!$C$28 | L16: =-Assumptions!$C$29*(1+Assumptions!$C$27)^7/Assumptions!$C$28 | M16: =-Assumptions!$C$29*(1+Assumptions!$C$27)^8/Assumptions!$C$28 | N16: =-Assumptions!$C$29*(1+Assumptions!$C$27)^9/Assumptions!$C$28 | O16: =-Assumptions!$C$29*(1+Assumptions!$C$27)^10/Assumptions!$C$28 | P16: =-Assumptions!$C$29*(1+Assumptions!$C$27)^11/Assumptions!$C$28 | Q16: =-Assumptions!$C$29*(1+Assumptions!$C$27)^12/Assumptions!$C$28 | R16: =-Assumptions!$C$29*(1+Assumptions!$C$27)^13/Assumptions!$C$28 | S16: =-Assumptions!$C$29*(1+Assumptions!$C$27)^14/Assumptions!$C$28 | T16: =-Assumptions!$C$29*(1+Assumptions!$C$27)^15/Assumptions!$C$28 | U16: =-Assumptions!$C$29*(1+Assumptions!$C$27)^16/Assumptions!$C$28 | V16: =-Assumptions!$C$29*(1+Assumptions!$C$27)^17/Assumptions!$C$28 | W16: =-Assumptions!$C$29*(1+Assumptions!$C$27)^18/Assumptions!$C$28 | X16: =-Assumptions!$C$29*(1+Assumptions!$C$27)^19/Assumptions!$C$28
B17: EBITDA | C17: =C12+C14+C15 | D17: =D12+D14+D15 | E17: =E12+E14+E15 | F17: =F12+F14+F15 | G17: =G12+G14+G15 | H17: =H12+H14+H15 | I17: =I12+I14+I15 | J17: =J12+J14+J15 | ... X17: =X12+X14+X15
B18: EBITDA margin | C18: 0 | D18: 0 | E18: =IF(E12=0,0,E17/E12) | F18: =IF(F12=0,0,F17/F12) | G18: =IF(G12=0,0,G17/G12) | H18: =IF(H12=0,0,H17/H12) | I18: =IF(I12=0,0,I17/I12) | J18: =IF(J12=0,0,J17/J12) | K18: =IF(K12=0,0,K17/K12) | L18: =IF(L12=0,0,L17/L12) | ... X18: =IF(X12=0,0,X17/X12)
B20: CAPITAL & FINANCING
B21: Capex | C21: =-Assumptions!$C$12*(1+Assumptions!$C$14)*Assumptions!$C$13 | D21: =-Assumptions!$C$12*(1+Assumptions!$C$14)*(1-Assumptions!$C$13) | E21: 0 | F21: 0 | G21: 0 | H21: 0 | I21: 0 | J21: 0 | K21: 0 | L21: 0 | M21: 0 | N21: 0 | O21: 0 | P21: 0 | Q21: 0 | R21: 0 | S21: 0 | T21: 0 | U21: 0 | V21: 0 | W21: 0 | X21: 0
B22: Cumulative capex | C22: =-C21 | D22: =C22-D21 | E22: =D22-E21 | F22: =E22-F21 | G22: =F22-G21 | H22: =G22-H21 | I22: =H22-I21 | J22: =I22-J21 | K22: =J22-K21 | ... X22: =W22-X21
B23: Depreciation (SLM) | C23: 0 | D23: 0 | E23: =-$D$22/Assumptions!$C$37 | F23: =-$D$22/Assumptions!$C$37 | G23: =-$D$22/Assumptions!$C$37 | H23: =-$D$22/Assumptions!$C$37 | I23: =-$D$22/Assumptions!$C$37 | J23: =-$D$22/Assumptions!$C$37 | K23: =-$D$22/Assumptions!$C$37 | L23: =-$D$22/Assumptions!$C$37 | ... X23: =-$D$22/Assumptions!$C$37
B24: Debt balance (opening) | C24: 0 | D24: =$D$22*Assumptions!$C$32 | E24: =MAX(0,D24+D26) | F24: =MAX(0,E24+E26) | G24: =MAX(0,F24+F26) | H24: =MAX(0,G24+G26) | I24: =MAX(0,H24+H26) | J24: =MAX(0,I24+I26) | K24: =MAX(0,J24+J26) | L24: =MAX(0,K24+K26) | ... X24: =MAX(0,W24+W26)
B25: Interest expense | C25: 0 | D25: 0 | E25: =-E24*Assumptions!$C$33 | F25: =-F24*Assumptions!$C$33 | G25: =-G24*Assumptions!$C$33 | H25: =-H24*Assumptions!$C$33 | I25: =-I24*Assumptions!$C$33 | J25: =-J24*Assumptions!$C$33 | K25: =-K24*Assumptions!$C$33 | L25: =-L24*Assumptions!$C$33 | ... X25: =-X24*Assumptions!$C$33
B26: Principal repayment | C26: 0 | D26: 0 | E26: =IF(0<Assumptions!$C$35,0,-MIN(E24,$D$24/(Assumptions!$C$34-Assumptions!$C$35))) | F26: =IF(1<Assumptions!$C$35,0,-MIN(F24,$D$24/(Assumptions!$C$34-Assumptions!$C$35))) | G26: =IF(2<Assumptions!$C$35,0,-MIN(G24,$D$24/(Assumptions!$C$34-Assumptions!$C$35))) | H26: =IF(3<Assumptions!$C$35,0,-MIN(H24,$D$24/(Assumptions!$C$34-Assumptions!$C$35))) | I26: =IF(4<Assumptions!$C$35,0,-MIN(I24,$D$24/(Assumptions!$C$34-Assumptions!$C$35))) | J26: =IF(5<Assumptions!$C$35,0,-MIN(J24,$D$24/(Assumptions!$C$34-Assumptions!$C$35))) | K26: =IF(6<Assumptions!$C$35,0,-MIN(K24,$D$24/(Assumptions!$C$34-Assumptions!$C$35))) | L26: =IF(7<Assumptions!$C$35,0,-MIN(L24,$D$24/(Assumptions!$C$34-Assumptions!$C$35))) | M26: =IF(8<Assumptions!$C$35,0,-MIN(M24,$D$24/(Assumptions!$C$34-Assumptions!$C$35))) | N26: =IF(9<Assumptions!$C$35,0,-MIN(N24,$D$24/(Assumptions!$C$34-Assumptions!$C$35))) | O26: =IF(10<Assumptions!$C$35,0,-MIN(O24,$D$24/(Assumptions!$C$34-Assumptions!$C$35))) | P26: =IF(11<Assumptions!$C$35,0,-MIN(P24,$D$24/(Assumptions!$C$34-Assumptions!$C$35))) | Q26: =IF(12<Assumptions!$C$35,0,-MIN(Q24,$D$24/(Assumptions!$C$34-Assumptions!$C$35))) | R26: =IF(13<Assumptions!$C$35,0,-MIN(R24,$D$24/(Assumptions!$C$34-Assumptions!$C$35))) | S26: =IF(14<Assumptions!$C$35,0,-MIN(S24,$D$24/(Assumptions!$C$34-Assumptions!$C$35))) | T26: =IF(15<Assumptions!$C$35,0,-MIN(T24,$D$24/(Assumptions!$C$34-Assumptions!$C$35))) | U26: =IF(16<Assumptions!$C$35,0,-MIN(U24,$D$24/(Assumptions!$C$34-Assumptions!$C$35))) | V26: =IF(17<Assumptions!$C$35,0,-MIN(V24,$D$24/(Assumptions!$C$34-Assumptions!$C$35))) | W26: =IF(18<Assumptions!$C$35,0,-MIN(W24,$D$24/(Assumptions!$C$34-Assumptions!$C$35))) | X26: =IF(19<Assumptions!$C$35,0,-MIN(X24,$D$24/(Assumptions!$C$34-Assumptions!$C$35)))
B28: RETURNS
B29: EBIT | C29: =C17+C23 | D29: =D17+D23 | E29: =E17+E23 | F29: =F17+F23 | G29: =G17+G23 | H29: =H17+H23 | I29: =I17+I23 | J29: =J17+J23 | ... X29: =X17+X23
B30: PBT | C30: =C29+C25 | D30: =D29+D25 | E30: =E29+E25 | F30: =F29+F25 | G30: =G29+G25 | H30: =H29+H25 | I30: =I29+I25 | J30: =J29+J25 | ... X30: =X29+X25
B31: Tax | C31: =-MAX(0,C30)*Assumptions!$C$36 | D31: =-MAX(0,D30)*Assumptions!$C$36 | E31: =-MAX(0,E30)*Assumptions!$C$36 | F31: =-MAX(0,F30)*Assumptions!$C$36 | G31: =-MAX(0,G30)*Assumptions!$C$36 | H31: =-MAX(0,H30)*Assumptions!$C$36 | I31: =-MAX(0,I30)*Assumptions!$C$36 | J31: =-MAX(0,J30)*Assumptions!$C$36 | ... X31: =-MAX(0,X30)*Assumptions!$C$36
B32: PAT | C32: =C30+C31 | D32: =D30+D31 | E32: =E30+E31 | F32: =F30+F31 | G32: =G30+G31 | H32: =H30+H31 | I32: =I30+I31 | J32: =J30+J31 | ... X32: =X30+X31
B34: Free Cash Flow to Firm | C34: =C17+C31+C21 | D34: =D17+D31+D21 | E34: =E17+E31+E21 | F34: =F17+F31+F21 | G34: =G17+G31+G21 | H34: =H17+H31+H21 | I34: =I17+I31+I21 | J34: =J17+J31+J21 | ... X34: =X17+X31+X21
B35: Free Cash Flow to Equity | C35: =C34+C25+C26+Assumptions!$C$12*(1+Assumptions!$C$14)*Assumptions!$C$32*Assumptions!$C$13 | D35: =D34+D25+D26+Assumptions!$C$12*(1+Assumptions!$C$14)*Assumptions!$C$32*(1-Assumptions!$C$13) | E35: =E34+E25+E26 | F35: =F34+F25+F26 | G35: =G34+G25+G26 | H35: =H34+H25+H26 | I35: =I34+I25+I26 | J35: =J34+J25+J26 | K35: =K34+K25+K26 | L35: =L34+L25+L26 | ... X35: =X34+X25+X26
B36: Discount factor | C36: =1/(1+Assumptions!$C$38)^1 | D36: =1/(1+Assumptions!$C$38)^2 | E36: =1/(1+Assumptions!$C$38)^3 | F36: =1/(1+Assumptions!$C$38)^4 | G36: =1/(1+Assumptions!$C$38)^5 | H36: =1/(1+Assumptions!$C$38)^6 | I36: =1/(1+Assumptions!$C$38)^7 | J36: =1/(1+Assumptions!$C$38)^8 | K36: =1/(1+Assumptions!$C$38)^9 | L36: =1/(1+Assumptions!$C$38)^10 | M36: =1/(1+Assumptions!$C$38)^11 | N36: =1/(1+Assumptions!$C$38)^12 | O36: =1/(1+Assumptions!$C$38)^13 | P36: =1/(1+Assumptions!$C$38)^14 | Q36: =1/(1+Assumptions!$C$38)^15 | R36: =1/(1+Assumptions!$C$38)^16 | S36: =1/(1+Assumptions!$C$38)^17 | T36: =1/(1+Assumptions!$C$38)^18 | U36: =1/(1+Assumptions!$C$38)^19 | V36: =1/(1+Assumptions!$C$38)^20 | W36: =1/(1+Assumptions!$C$38)^21 | X36: =1/(1+Assumptions!$C$38)^22
B37: PV of FCFF | C37: =C34*C36 | D37: =D34*D36 | E37: =E34*E36 | F37: =F34*F36 | G37: =G34*G36 | H37: =H34*H36 | I37: =I34*I36 | J37: =J34*J36 | ... X37: =X34*X36
B38: Cumulative PV | C38: =C37 | D38: =C38+D37 | E38: =D38+E37 | F38: =E38+F37 | G38: =F38+G37 | H38: =G38+H37 | I38: =H38+I37 | J38: =I38+J37 | K38: =J38+K37 | ... X38: =W38+X37
B40: DSCR (smoothed CFADS / debt service) | C40: 0 | D40: 0 | E40: =IF((E25+E26)=0,"",(E17-E15+E16+E31)/-(E25+E26)) | F40: =IF((F25+F26)=0,"",(F17-F15+F16+F31)/-(F25+F26)) | G40: =IF((G25+G26)=0,"",(G17-G15+G16+G31)/-(G25+G26)) | H40: =IF((H25+H26)=0,"",(H17-H15+H16+H31)/-(H25+H26)) | I40: =IF((I25+I26)=0,"",(I17-I15+I16+I31)/-(I25+I26)) | J40: =IF((J25+J26)=0,"",(J17-J15+J16+J31)/-(J25+J26)) | K40: =IF((K25+K26)=0,"",(K17-K15+K16+K31)/-(K25+K26)) | L40: =IF((L25+L26)=0,"",(L17-L15+L16+L31)/-(L25+L26)) | ... X40: =IF((X25+X26)=0,"",(X17-X15+X16+X31)/-(X25+X26))

Sheet Returns
B2: RETURNS SUMMARY
B4: Total project cost (incl. contingency) | C4: =Assumptions!C12*(1+Assumptions!C14) | D4: Equity + debt funded
B5: Peak net revenue (final year) | C5: ='Cash Flow'!X12 | D5: Terminal-year toll income
B7: NPV @ WACC | C7: =SUM('Cash Flow'!C37:X37) | D7: Positive = project creates value at the hurdle rate
B8: Project IRR (FCFF) | C8: =IRR('Cash Flow'!C34:X34) | D8: Compare against WACC
B9: Equity IRR (FCFE) | C9: =IRR('Cash Flow'!C35:X35) | D9: Compare against cost of equity
B11: WACC (hurdle) | C11: =Assumptions!C38 | D11: From Assumptions
B12: Spread over WACC | C12: =IRR('Cash Flow'!C34:X34)-Assumptions!C38 | D12: Project IRR less hurdle rate
B14: Minimum DSCR (operating years) | C14: =MIN('Cash Flow'!E40:X40) | D14: Lenders typically covenant a floor around 1.20x-1.30x
B15: Average DSCR (operating years) | C15: =AVERAGE('Cash Flow'!E40:X40) | D15: Debt service headroom
B17: DSCR covenant floor (lender) | C17: =0.2*6 | D17: Illustrative 1.20x floor - typical for Indian BOT term loans
B18: Operating years breaching 1.20x | C18: =COUNTIF('Cash Flow'!E40:X40,"<1.2") | D18: Years where CFADS fails the covenant - drives DSRA sizing
B20: Discounted payback (year) | C20: =IFERROR(MATCH(TRUE(),INDEX('Cash Flow'!C38:X38>0,0),0),"beyond concession") | D20: First year cumulative PV turns positive
B23: SENSITIVITY — Project IRR
B24: Rows: traffic CAGR | Columns: toll escalation
B25: Traffic \ Toll | C25: 0.02 | D25: 0.03 | E25: 0.04 | F25: 0.05 | G25: 0.06
B26: 0.035 | C26: 0.101076 | D26: 0.115282 | E26: 0.128282 | F26: 0.140666 | G26: 0.152479
B27: 0.045 | C27: 0.115086 | D27: 0.128221 | E27: 0.140724 | F27: 0.152646 | G27: 0.164141
B28: 0.055 | C28: 0.127916 | D28: 0.140548 | E28: 0.15259 | F28: 0.164195 | G28: 0.175525
B29: 0.065 | C29: 0.140137 | D29: 0.152311 | E29: 0.164032 | F29: 0.175472 | G29: 0.186677
B30: 0.075 | C30: 0.151809 | D30: 0.163652 | E30: 0.175206 | F30: 0.186521 | G30: 0.197632
B32: Sensitivity grid is populated by the Monte Carlo script (run_monte_carlo.py) — values written as static results.
